iauto/__init__.py
iauto/desktop/__init__.py
iauto_desktop-0.1.0.dist-info/METADATA
iauto_desktop-0.1.0.dist-info/WHEEL
iauto_desktop-0.1.0.dist-info/entry_points.txt
iauto_desktop-0.1.0.dist-info/top_level.txt
iauto_desktop-0.1.0.dist-info/RECORD
