Metadata-Version: 2.1
Name: iauto-desktop
Version: 0.1.0
Summary: iauto-desktop is a desktop application for iauto
Home-page: https://github.com/shellc/ia-desktop
Author: shellc
Author-email: shenggong.wang@gmail.com
License: MIT
Keywords: AI,Automation,LLM,RPA
Classifier: Programming Language :: Python :: 3
Requires-Python: >=3.8
Requires-Dist: iauto
